django_hookup/__init__.py
django_hookup/apps.py
django_hookup/core.py
django_hookup/urls.py
django_hookup/version.py
django_hookup/templates/admin/hooks_registry.html
django_hookup-0.0.2.dist-info/LICENCE
django_hookup-0.0.2.dist-info/METADATA
django_hookup-0.0.2.dist-info/WHEEL
django_hookup-0.0.2.dist-info/top_level.txt
django_hookup-0.0.2.dist-info/RECORD
