Metadata-Version: 2.1
Name: django-hookup
Version: 0.0.2
Summary: Simple Django Hooks
Home-page: https://github.com/realnoobs/django_hookup
Author: Rizki Sasri Dwitama
Author-email: sasri.project@gmail.com
License: MIT
Project-URL: Documentation, https://github.com/realnoobs/django_hookup
Project-URL: Source, https://github.com/realnoobs/django_hookup
Platform: UNKNOWN
Classifier: Environment :: Web Environment
Classifier: Framework :: Django
Classifier: Intended Audience :: Developers
Classifier: License :: OSI Approved :: MIT License
Classifier: Operating System :: OS Independent
Classifier: Programming Language :: Python
Classifier: Programming Language :: Python :: 3
Classifier: Programming Language :: Python :: 3 :: Only
Classifier: Programming Language :: Python :: 3.8
Classifier: Programming Language :: Python :: 3.9
Classifier: Topic :: Internet :: WWW/HTTP
Classifier: Topic :: Internet :: WWW/HTTP :: Dynamic Content
Classifier: Topic :: Internet :: WWW/HTTP :: WSGI
Classifier: Topic :: Software Development :: Libraries :: Python Modules
Classifier: Topic :: Software Development :: Libraries :: Application Frameworks
Requires-Python: >=3.6
License-File: LICENCE
Requires-Dist: Django (<4.0,>=3.2.7)
